log_creator/Log.py
log_creator/Logging.py
log_creator/__init__.py
log_creator/logger.py
log_creator-0.0.15.dist-info/METADATA
log_creator-0.0.15.dist-info/WHEEL
log_creator-0.0.15.dist-info/top_level.txt
log_creator-0.0.15.dist-info/RECORD
