Metadata-Version: 2.1
Name: log-creator
Version: 0.0.15
Summary: Log Creator Module
Home-page: UNKNOWN
Author: lUckYtHRteeN13 (Nethan Quinn Jael) 
Author-email: <nethanquinnjael13@gmail.com>
License: UNKNOWN
Keywords: python,log,logs,log creator
Platform: UNKNOWN
Classifier: Development Status :: 1 - Planning
Classifier: Intended Audience :: Developers
Classifier: Programming Language :: Python :: 3
Classifier: Operating System :: Microsoft :: Windows
